numba_extinction/__init__.py
numba_extinction/numba_extinction.py
numba_extinction/models/__init__.py
numba_extinction/models/calzetti_00.py
numba_extinction/models/ccm_89.py
numba_extinction/models/fitzpatrick_99.py
numba_extinction/models/fm07.py
numba_extinction/models/gordon_23.py
numba_extinction/models/odonnell_94.py
numba_extinction/models/vcg_04.py
numba_extinction/utils/__init__.py
numba_extinction/utils/cubic_spline.py
numba_extinction/utils/helpers.py
numba_extinction-0.1.3.1.dist-info/METADATA
numba_extinction-0.1.3.1.dist-info/WHEEL
numba_extinction-0.1.3.1.dist-info/licenses/LICENSE
numba_extinction-0.1.3.1.dist-info/RECORD
