Metadata-Version: 2.4
Name: numba_extinction
Version: 0.1.3.1
Summary: `extinction.py` rewritten and extended using Numba.
Project-URL: Homepage, https://github.com/G-Francio/numba_extinction
Project-URL: Bug Tracker, https://github.com/G-Francio/numba_extinction/issues
Author-email: Francesco Guarneri <francesco.guarneri@uni-hamburg.de>
License: MIT License
License-File: LICENSE
Keywords: astronomy,python,science
Classifier: Development Status :: 4 - Beta
Classifier: Intended Audience :: Science/Research
Classifier: License :: OSI Approved :: MIT License
Classifier: Operating System :: OS Independent
Classifier: Programming Language :: Python :: 3.12
Classifier: Topic :: Scientific/Engineering :: Astronomy
Classifier: Topic :: Scientific/Engineering :: Physics
Requires-Python: >=3.12
Requires-Dist: astropy>=7.1.1
Requires-Dist: numba>=0.62.1
Requires-Dist: numpy>=2.3.4
Provides-Extra: ipython
Requires-Dist: ipython>=9.7.0; extra == 'ipython'
Requires-Dist: ipywidgets>=8.1.8; extra == 'ipython'
Requires-Dist: jupyterlab>=4.4.10; extra == 'ipython'
Requires-Dist: matplotlib>=3.10.7; extra == 'ipython'
Provides-Extra: plot
Requires-Dist: dust-extinction>=1.6; extra == 'plot'
Requires-Dist: extinction>=0.4.8; extra == 'plot'
Requires-Dist: matplotlib>=3.10.7; extra == 'plot'
